flowcompass/__init__.py
flowcompass/main.py
flowcompass-0.1.3.dist-info/licenses/LICENSE
flowcompass-0.1.3.dist-info/METADATA
flowcompass-0.1.3.dist-info/WHEEL
flowcompass-0.1.3.dist-info/entry_points.txt
flowcompass-0.1.3.dist-info/top_level.txt
flowcompass-0.1.3.dist-info/RECORD
