Metadata-Version: 2.4
Name: flowcompass
Version: 0.1.3
Summary: A tool to generate flow diagrams from source code
Home-page: https://github.com/krishnapd1/flowcompass
Author: Krishna Prasad
Author-email: krishnapd883@gmail.com
Classifier: Programming Language :: Python :: 3
Classifier: License :: OSI Approved :: MIT License
Classifier: Operating System :: OS Independent
Requires-Python: >=3.6
License-File: LICENSE
Dynamic: author
Dynamic: author-email
Dynamic: classifier
Dynamic: description
Dynamic: description-content-type
Dynamic: home-page
Dynamic: license-file
Dynamic: requires-python
Dynamic: summary
